README.md
__init__.py
recordparser.py
setup.py
test.py
recordparser.egg-info/PKG-INFO
recordparser.egg-info/SOURCES.txt
recordparser.egg-info/dependency_links.txt
recordparser.egg-info/top_level.txt