Metadata-Version: 2.1
Name: recordparser
Version: 0.1.0
Summary: Parse delimited text files using typed class
Home-page: https://github.com/kyclark/python-recordparser
Author: Ken Youens-Clark
Author-email: kyclark@gmail.com
License: UNKNOWN
Platform: UNKNOWN
Classifier: Programming Language :: Python :: 3
Classifier: License :: OSI Approved :: MIT License
Classifier: Operating System :: OS Independent
